configz/__init__.py
configz/consts.py
configz/deepmerge.py
configz/dump_universal.py
configz/exceptions.py
configz/json_tools/__init__.py
configz/json_tools/base.py
configz/json_tools/msgspec_provider/__init__.py
configz/json_tools/msgspec_provider/provider.py
configz/json_tools/orjson_provider/__init__.py
configz/json_tools/orjson_provider/provider.py
configz/json_tools/pydantic_provider/__init__.py
configz/json_tools/pydantic_provider/provider.py
configz/json_tools/stdlib_provider/__init__.py
configz/json_tools/stdlib_provider/provider.py
configz/json_tools/utils.py
configz/load_universal.py
configz/log.py
configz/parse_errors.py
configz/py.typed
configz/toml_tools/__init__.py
configz/toml_tools/base.py
configz/toml_tools/pytomlpp_provider/__init__.py
configz/toml_tools/pytomlpp_provider/provider.py
configz/toml_tools/rtoml_provider/__init__.py
configz/toml_tools/rtoml_provider/provider.py
configz/toml_tools/toml_rs_provider/__init__.py
configz/toml_tools/toml_rs_provider/provider.py
configz/toml_tools/tomllib_provider/__init__.py
configz/toml_tools/tomllib_provider/provider.py
configz/typedefs.py
configz/utils.py
configz/validate.py
configz/verify.py
configz/yaml_tools/__init__.py
configz/yaml_tools/constructors/__init__.py
configz/yaml_tools/constructors/variable.py
configz/yaml_tools/jinja_tag.py
configz/yaml_tools/yaml_dumpers.py
configz/yaml_tools/yaml_errors.py
configz/yaml_tools/yaml_loaders.py
configz/yaml_tools/yamlparser.py
configz-3.0.1.dist-info/licenses/LICENSE
configz-3.0.1.dist-info/WHEEL
configz-3.0.1.dist-info/entry_points.txt
configz-3.0.1.dist-info/METADATA
configz-3.0.1.dist-info/RECORD
