Metadata-Version: 2.4
Name: configz
Version: 3.0.1
Summary: Serialization stuff for config files
Keywords: PyYAML,include,serialization,yaml,yml
Author: Philipp Temminghoff
Author-email: Philipp Temminghoff <philipptemminghoff@googlemail.com>
License-Expression: MIT
License-File: LICENSE
Classifier: Development Status :: 4 - Beta
Classifier: Intended Audience :: Developers
Classifier: Operating System :: OS Independent
Classifier: Programming Language :: Python :: 3
Classifier: Programming Language :: Python :: 3 :: Only
Classifier: Programming Language :: Python :: 3.12
Classifier: Programming Language :: Python :: 3.13
Classifier: Programming Language :: Python :: 3.14
Classifier: Topic :: Documentation
Classifier: Topic :: Software Development
Classifier: Topic :: Utilities
Classifier: Typing :: Typed
Requires-Dist: pyyaml>=5.1
Requires-Dist: fsspec
Requires-Dist: pydantic
Requires-Dist: pyyaml-include
Requires-Dist: universal-pathlib
Requires-Dist: upathtools>=0.6.4
Requires-Dist: jinja2 ; extra == 'all'
Requires-Dist: tomli-w ; extra == 'all'
Requires-Dist: rich ; extra == 'exceptions'
Requires-Dist: jinja2 ; extra == 'jinja2'
Requires-Dist: msgspec ; extra == 'msgspec'
Requires-Dist: pytomlpp ; python_full_version < '3.14' and extra == 'pytomlpp'
Requires-Dist: rtoml ; extra == 'rtoml'
Requires-Dist: tomli-w ; extra == 'toml'
Requires-Dist: toml-rs ; extra == 'toml-rs'
Requires-Dist: python-toon ; extra == 'toon'
Requires-Python: >=3.13
Project-URL: Code coverage, https://app.codecov.io/gh/phil65/configz
Project-URL: Discussions, https://github.com/phil65/configz/discussions
Project-URL: Documentation, https://phil65.github.io/configz/
Project-URL: Issues, https://github.com/phil65/configz/issues
Project-URL: Source, https://github.com/phil65/configz
Provides-Extra: all
Provides-Extra: exceptions
Provides-Extra: jinja2
Provides-Extra: msgspec
Provides-Extra: pytomlpp
Provides-Extra: rtoml
Provides-Extra: toml
Provides-Extra: toml-rs
Provides-Extra: toon
